MANIFEST.in
README.md
setup.py
mocks/__init__.py
mocks/core.py
mocks/gpio.py
mocks/sensors.py
robot_blocks.egg-info/PKG-INFO
robot_blocks.egg-info/SOURCES.txt
robot_blocks.egg-info/dependency_links.txt
robot_blocks.egg-info/requires.txt
robot_blocks.egg-info/top_level.txt
robotblocks/__init__.py
robotblocks/core.py
robotblocks/movement.py
robotblocks/hardware/__init__.py
robotblocks/hardware/motors.py
robotblocks/hardware/sensors.py