Metadata-Version: 1.1
Name: robot-blocks
Version: 0.1.0a8
Summary: Building blocks for raspberry pi robot software
Home-page: https://chris104957.github.io/robot-blocks/
Author: Christopher Davies
Author-email: christopherdavies553@gmail.com
License: Apache Software License
Platform: UNKNOWN
Classifier: Development Status :: 3 - Alpha
Classifier: Framework :: Robot Framework
Classifier: Framework :: Robot Framework :: Library
Classifier: Intended Audience :: Developers
Classifier: License :: OSI Approved :: Apache Software License
Classifier: Operating System :: OS Independent
Classifier: Programming Language :: Python
Classifier: Programming Language :: Python :: 3.5
Classifier: Programming Language :: Python :: 3.6
